{"type":"Topology","objects":{"geo":{"type":"GeometryCollection","geometries":[{"type":"Polygon","arcs":[[0,1,2,3,4,5]],"properties":{"code":"11100","name":"さいたま市"}},{"type":"Polygon","arcs":[[6,7,8,-5]],"properties":{"code":"11100","name":"さいたま市"}},{"type":"Polygon","arcs":[[9,10,11,12,-7,-4]],"properties":{"code":"11100","name":"さいたま市"}},{"type":"Polygon","arcs":[[-13,13,14,15,16,17,-8]],"properties":{"code":"11100","name":"さいたま市"}},{"type":"Polygon","arcs":[[18,19,20,-11]],"properties":{"code":"11100","name":"さいたま市"}},{"type":"Polygon","arcs":[[21,22,23,24,-19,-10,-3]],"properties":{"code":"11100","name":"さいたま市"}},{"type":"Polygon","arcs":[[-21,25,26,-14,-12]],"properties":{"code":"11100","name":"さいたま市"}},{"type":"Polygon","arcs":[[-25,27,28,29,30,31,-26,-20]],"properties":{"code":"11100","name":"さいたま市"}},{"type":"Polygon","arcs":[[-27,-32,32,33,-15]],"properties":{"code":"11100","name":"さいたま市"}},{"type":"Polygon","arcs":[[-34,34,35,36,37,38,-16]],"properties":{"code":"11100","name":"さいたま市"}},{"type":"Polygon","arcs":[[39,40,41,42,43,44,45,46,47,-1,48]],"properties":{"code":"11201","name":"川越市"}},{"type":"Polygon","arcs":[[49,50,51,52,53,54,55,56]],"properties":{"code":"11202","name":"熊谷市"}},{"type":"Polygon","arcs":[[57,58,59,60,61,-35,-33,-31]],"properties":{"code":"11203","name":"川口市"}},{"type":"Polygon","arcs":[[62,63,64,65,-57]],"properties":{"code":"11206","name":"行田市"}},{"type":"Polygon","arcs":[[66,67,68,69,70,71,72,73,74]],"properties":{"code":"11207","name":"秩父市"}},{"type":"Polygon","arcs":[[75,76,77,78,79,-45]],"properties":{"code":"11208","name":"所沢市"}},{"type":"Polygon","arcs":[[80,81,82,83,84,85,86,87,-70]],"properties":{"code":"11209","name":"飯能市"}},{"type":"Polygon","arcs":[[88,89,90,91,-64]],"properties":{"code":"11210","name":"加須市"}},{"type":"Polygon","arcs":[[92,93,94,95,96,97,98]],"properties":{"code":"11211","name":"本庄市"}},{"type":"Polygon","arcs":[[99,100,101,102,103,104,-54]],"properties":{"code":"11212","name":"東松山市"}},{"type":"Polygon","arcs":[[105,106,107,108,109,110,-37]],"properties":{"code":"11214","name":"春日部市"}},{"type":"Polygon","arcs":[[111,-83,112,-76,-44]],"properties":{"code":"11215","name":"狭山市"}},{"type":"Polygon","arcs":[[-92,113,-65]],"properties":{"code":"11216","name":"羽生市"}},{"type":"Polygon","arcs":[[114,115,116,117,-89,-63,-56]],"properties":{"code":"11217","name":"鴻巣市"}},{"type":"Polygon","arcs":[[118,-99,119,120,121,-51]],"properties":{"code":"11218","name":"深谷市"}},{"type":"Polygon","arcs":[[-6,-9,-18,122,123,124,125,-49]],"properties":{"code":"11219","name":"上尾市"}},{"type":"Polygon","arcs":[[126,127,128,129,130,-61]],"properties":{"code":"11221","name":"草加市"}},{"type":"Polygon","arcs":[[-62,-131,131,132,-106,-36]],"properties":{"code":"11222","name":"越谷市"}},{"type":"Polygon","arcs":[[133,-58,-30]],"properties":{"code":"11223","name":"蕨市"}},{"type":"Polygon","arcs":[[134,135,136,-59,-134,-29]],"properties":{"code":"11224","name":"戸田市"}},{"type":"Polygon","arcs":[[-113,-82,137,-77]],"properties":{"code":"11225","name":"入間市"}},{"type":"Polygon","arcs":[[138,139,140,141,-135,-28,-24]],"properties":{"code":"11227","name":"朝霞市"}},{"type":"Polygon","arcs":[[142,143,144,-139,-23]],"properties":{"code":"11228","name":"志木市"}},{"type":"Polygon","arcs":[[-142,145,-136]],"properties":{"code":"11229","name":"和光市"}},{"type":"Polygon","arcs":[[146,-140,-145,147,-79]],"properties":{"code":"11230","name":"新座市"}},{"type":"Polygon","arcs":[[148,149,-125,150,151,152,-117]],"properties":{"code":"11231","name":"桶川市"}},{"type":"Polygon","arcs":[[-118,-153,153,154,155,156,157,158,-90]],"properties":{"code":"11232","name":"久喜市"}},{"type":"Polygon","arcs":[[159,160,-149,-116]],"properties":{"code":"11233","name":"北本市"}},{"type":"Polygon","arcs":[[161,162,-128]],"properties":{"code":"11234","name":"八潮市"}},{"type":"Polygon","arcs":[[-48,163,164,-143,-22,-2]],"properties":{"code":"11235","name":"富士見市"}},{"type":"Polygon","arcs":[[-163,165,166,-129]],"properties":{"code":"11237","name":"三郷市"}},{"type":"Polygon","arcs":[[-39,167,-154,-152,168,-123,-17]],"properties":{"code":"11238","name":"蓮田市"}},{"type":"Polygon","arcs":[[169,-103,170,171,172,173,-41]],"properties":{"code":"11239","name":"坂戸市"}},{"type":"Polygon","arcs":[[174,175,-158]],"properties":{"code":"11240","name":"幸手市"}},{"type":"Polygon","arcs":[[-174,176,-42]],"properties":{"code":"11241","name":"鶴ヶ島市"}},{"type":"Polygon","arcs":[[-177,-173,177,-84,-112,-43]],"properties":{"code":"11242","name":"日高市"}},{"type":"Polygon","arcs":[[-167,178,179,-132,-130]],"properties":{"code":"11243","name":"吉川市"}},{"type":"Polygon","arcs":[[180,-164,-47]],"properties":{"code":"11245","name":"ふじみ野市"}},{"type":"Polygon","arcs":[[-111,181,-155,-168,-38]],"properties":{"code":"11246","name":"白岡市"}},{"type":"Polygon","arcs":[[-169,-151,-124]],"properties":{"code":"11301","name":"伊奈町"}},{"type":"Polygon","arcs":[[-80,-148,-144,-165,-181,-46]],"properties":{"code":"11324","name":"三芳町"}},{"type":"Polygon","arcs":[[-178,-172,182,183,-85]],"properties":{"code":"11326","name":"毛呂山町"}},{"type":"Polygon","arcs":[[-184,184,185,-86]],"properties":{"code":"11327","name":"越生町"}},{"type":"Polygon","arcs":[[186,-100,-53]],"properties":{"code":"11341","name":"滑川町"}},{"type":"Polygon","arcs":[[-122,187,188,189,190,-101,-187,-52]],"properties":{"code":"11342","name":"嵐山町"}},{"type":"Polygon","arcs":[[191,192,193,-189]],"properties":{"code":"11343","name":"小川町"}},{"type":"Polygon","arcs":[[-126,-150,-161,194,-104,-170,-40]],"properties":{"code":"11346","name":"川島町"}},{"type":"Polygon","arcs":[[-105,-195,-160,-115,-55]],"properties":{"code":"11347","name":"吉見町"}},{"type":"Polygon","arcs":[[-191,195,-185,-183,-171,-102]],"properties":{"code":"11348","name":"鳩山町"}},{"type":"Polygon","arcs":[[196,-87,-186,-196,-190,-194,197,-72]],"properties":{"code":"11349","name":"ときがわ町"}},{"type":"Polygon","arcs":[[-88,-197,-71]],"properties":{"code":"11361","name":"横瀬町"}},{"type":"Polygon","arcs":[[198,199,200,-96,201,-74]],"properties":{"code":"11362","name":"皆野町"}},{"type":"Polygon","arcs":[[-201,202,203,-97]],"properties":{"code":"11363","name":"長瀞町"}},{"type":"Polygon","arcs":[[204,-68]],"properties":{"code":"11365","name":"小鹿野町"}},{"type":"Polygon","arcs":[[-198,-193,205,-199,-73]],"properties":{"code":"11369","name":"東秩父村"}},{"type":"Polygon","arcs":[[-204,206,-120,-98]],"properties":{"code":"11381","name":"美里町"}},{"type":"Polygon","arcs":[[-202,-95,207,208,-75]],"properties":{"code":"11383","name":"神川町"}},{"type":"Polygon","arcs":[[209,-208,-94]],"properties":{"code":"11385","name":"上里町"}},{"type":"Polygon","arcs":[[-207,-203,-200,-206,-192,-188,-121]],"properties":{"code":"11408","name":"寄居町"}},{"type":"Polygon","arcs":[[210,-156,-182,-110]],"properties":{"code":"11442","name":"宮代町"}},{"type":"Polygon","arcs":[[211,-175,-157,-211,-109]],"properties":{"code":"11464","name":"杉戸町"}},{"type":"Polygon","arcs":[[-133,-180,212,-107]],"properties":{"code":"11465","name":"松伏町"}}]}},"arcs":[[[70398,34431],[-132,-2340],[735,-3471],[-459,-3133]],[[70542,25487],[851,-1272],[-56,-1227],[1480,-504]],[[72817,22484],[-315,1694],[2111,49],[495,1321]],[[75108,25548],[-536,660],[-6,4569]],[[74566,30777],[3,4117]],[[74569,34894],[-916,1741],[-965,-314],[-1539,-1665],[-751,-225]],[[74566,30777],[1225,248],[566,1082],[1948,429]],[[78305,32536],[68,2856],[-1410,2507]],[[76963,37899],[-1018,2592],[-1141,-1246],[-998,156],[905,-3081],[-142,-1426]],[[75108,25548],[50,201]],[[75158,25749],[265,1410],[2401,-1299]],[[77824,25860],[955,122],[88,2219]],[[78867,28201],[-41,2051],[-521,2284]],[[78867,28201],[1060,-1458]],[[79927,26743],[738,584],[1627,-244],[1002,625],[-691,2454],[653,748]],[[83256,30910],[-810,2794],[-522,505],[-212,3135],[-1058,2682],[-981,68]],[[79673,40094],[-758,-327]],[[78915,39767],[-302,-2068],[-699,727],[-951,-527]],[[75158,25749],[471,-703],[755,-3004],[1471,-1669]],[[77855,20373],[329,-432]],[[78184,19941],[-360,5919]],[[72817,22484],[730,-2087]],[[73547,20397],[1875,-4901]],[[75422,15496],[772,-146]],[[76194,15350],[1630,1336],[-232,1975],[263,1712]],[[78184,19941],[1583,-2107],[672,1052],[-53,1666]],[[80386,20552],[174,4212],[-633,1979]],[[76194,15350],[180,-934]],[[76374,14416],[2636,707],[1119,-722]],[[80129,14401],[1163,701]],[[81292,15102],[-157,3392],[1725,-368],[197,1681]],[[83057,19807],[-289,1141],[-1358,645],[-1024,-1041]],[[83057,19807],[510,936],[1158,-5],[198,1528],[-561,1218],[2296,-78],[215,1835]],[[86873,25241],[-1039,2479],[-1125,1890],[-1453,1300]],[[86873,25241],[752,-1075]],[[87625,24166],[-594,2557],[694,393],[87,2799],[-791,1335],[771,3420],[-196,966]],[[87596,35636],[-521,2233],[-2122,1166],[-605,1370],[949,1361],[-14,2476],[-1400,1825]],[[83883,46067],[-1339,709]],[[82544,46776],[306,-1514],[-948,-2946],[-1538,-2],[-691,-2220]],[[69457,37084],[-2844,1407],[-1966,163],[-992,704]],[[63655,39358],[-1433,-2235],[-1342,-613],[-303,2623],[-816,-595]],[[59761,38538],[620,-2956],[-1423,-3093],[-1915,-1860],[-818,1084]],[[56225,31713],[418,-2173],[686,-51],[755,-2395]],[[58084,27094],[856,998],[2492,-3051],[1068,-1663],[676,325],[319,-2054],[-591,-1529],[1455,-3641]],[[64359,16479],[156,-446]],[[64515,16033],[774,848]],[[65289,16881],[-176,1430],[-874,1072],[1765,1755],[1295,2930],[292,1579],[1148,-1303],[1605,-26]],[[70344,24318],[198,1169]],[[70398,34431],[-355,680],[-586,1973]],[[61677,84433],[-2117,3743],[-2160,2129],[-1411,3214],[-1553,1680],[-2557,-2561]],[[51879,92638],[642,-1358],[80,-2879],[-359,-6151],[-1207,-2116],[-450,698],[-1385,-2105],[-235,-967],[1814,-2893],[-227,-1558],[-66,-4076],[-852,-1260]],[[49634,67973],[675,-975],[984,-2794]],[[51293,64204],[1795,-109],[140,2596],[2693,-831],[950,479]],[[56871,66339],[649,-102],[1512,-2094],[-366,-2689],[1106,-1232]],[[59772,60222],[2008,2075],[100,580]],[[61880,62877],[-1151,1721],[-99,3440]],[[60630,68038],[-54,3984],[-712,1355],[-25,1692],[943,-77],[-129,2175],[251,2238],[-1140,207],[-219,3422],[352,1560],[1780,-161]],[[81292,15102],[2758,-1216],[-870,-2092]],[[83180,11794],[-155,-3214]],[[83025,8580],[970,-1223],[2079,-376],[333,-1812],[1446,1212],[486,2002],[-852,1763],[1429,2098]],[[88916,12244],[1741,1331],[-776,1598],[-35,1732],[-617,1204],[-651,2836],[526,559]],[[89104,21504],[-1479,2662]],[[60630,68038],[795,1282],[1457,-1105],[629,224],[1112,-1770],[717,-2281],[488,75],[759,2267],[-482,1498],[786,683],[363,1790],[1728,-1334]],[[68982,69367],[387,1704],[-936,2209]],[[68433,73280],[-682,-19],[-380,3064],[-1147,275],[-47,1260],[-809,2031],[1149,1868],[-519,1872]],[[65998,83631],[-1776,-594],[-1691,372],[-854,1024]],[[22284,69280],[-546,1338],[-973,-28],[-160,-3502],[-991,-2135],[-1155,-1213]],[[18459,63740],[197,-1770],[1806,-3631],[1486,-1255],[-268,-1882],[1241,-1702],[2130,-1233],[1246,-2261],[1173,862],[1024,-234],[65,-1899],[-860,-1447],[817,-1851],[-584,-2430],[-1236,-1940],[-1369,-464],[-355,2489],[-1299,-667],[-959,1281],[-646,-725],[-1329,104],[-618,-1860],[-934,-585],[-1070,633],[-732,-386],[-1653,1393],[-1676,-69],[-1847,2231],[-1330,2626],[-241,3422],[301,2274],[-1128,1300]],[[9811,54064],[-2207,-743],[-945,-762],[-871,1419],[-968,373],[-1240,-816],[-897,-4651],[-977,-2241],[-1294,-1034],[-412,-2615],[191,-2600],[962,-1505],[466,-2374],[684,-1150],[-63,-1921],[-792,-2245],[-18,-1428],[1703,-1546],[2362,-227],[1007,-1366],[662,-4020],[963,-402],[438,-1457],[2682,956],[942,-528],[183,-1341],[895,-62],[865,-1966],[1039,-1348],[1593,2453],[1299,-725],[1479,1123],[-90,1018],[971,2669],[2066,2062],[533,-728],[1306,536],[824,2494],[1096,50],[2214,-3528],[1913,-1354],[841,600],[1494,-1463]],[[32710,21671],[660,1055],[207,1778],[862,2532],[-745,2375],[45,2273],[-820,1419]],[[32919,33103],[-613,1657],[133,3163],[-717,2497],[-122,1876],[626,4207],[997,2153],[730,-1873],[925,394],[2754,-1205],[1338,-1097]],[[38970,44875],[134,1653]],[[39104,46528],[-766,1529],[-1209,4024]],[[37129,52081],[-2381,1611],[-502,1399],[-272,2481],[-627,789],[-1026,-409],[-948,1590],[-2251,-1183],[-205,2451],[-936,322],[-752,-839],[-1288,1523],[-475,1350],[-874,539],[326,1814]],[[24918,65519],[-1223,-412],[-1411,4173]],[[64359,16479],[-1068,700],[-1144,-2481],[-1444,-1722],[-1110,-705]],[[59593,12271],[-1554,-1643],[-1260,-683],[270,-1111],[-286,-2190],[793,-1136],[-135,-1357],[-1027,-174]],[[56394,3977],[-106,-1503],[1535,-375],[542,905],[1236,-620],[2140,144],[2206,1284],[702,1244],[2292,540],[1900,2163],[1047,2509]],[[69888,10268],[324,1002],[-927,1259]],[[69285,12529],[-191,1110],[-2452,-2038],[-1744,4650],[-383,-218]],[[32710,21671],[965,-478],[1990,135],[2024,-1585],[324,-1161],[2459,-2037],[1702,1207],[1675,-1899],[1661,307],[695,-428],[1797,670],[1628,-868],[119,-2078],[1139,-1006]],[[50888,12450],[862,1459],[1612,234],[-64,4252],[459,1713],[902,76]],[[54659,20184],[1165,1710]],[[55824,21894],[-2403,2329],[-966,-423],[-599,795],[-2656,-2676],[-1155,273],[-582,910],[315,1496],[-168,3427]],[[47610,28025],[-344,2349],[-828,2153]],[[46438,32527],[-835,-400],[-1389,1550],[-737,2935],[-1279,2055]],[[42198,38667],[-960,1776],[-1930,754]],[[39308,41197],[-890,-3827],[-2042,-1441],[-2279,-2143],[-1178,-683]],[[68982,69367],[580,-2268],[1124,-968],[-940,-3581],[1097,-508],[550,-1415]],[[71393,60627],[1398,-79],[851,1208],[588,-932],[874,2728],[2060,-1392],[974,1388],[514,2008],[1902,1785],[-344,1828],[1782,1898],[-67,1952],[1551,1572]],[[83476,74591],[-582,2150],[-441,3592],[233,3126],[-596,2216],[-982,948],[-1035,-222],[-1114,774],[177,-2440],[-1201,-222],[-1568,-1410],[-736,1334]],[[75631,84437],[-577,-2026],[848,-2800],[-506,-2322],[-1472,922],[-279,-2601],[-1152,-56],[16,-1365],[-814,-1184],[-3262,275]],[[44793,93520],[-1662,2626],[-999,-374],[-3595,3507]],[[38537,99279],[-305,-2863],[-864,-1849],[1045,-2062],[-1568,-2339],[-1131,-1074]],[[35714,89092],[-680,-2741],[-1572,70],[98,-1524],[-1168,-1076],[-1776,-3183],[76,-2901],[-735,85],[-59,-3610],[-846,-3221]],[[29052,70991],[1212,-1388],[953,518]],[[31217,70121],[461,1876],[1511,2328],[782,-111],[950,995],[853,-512]],[[35774,74697],[829,1395],[-305,2129],[977,2307],[-173,1159],[693,2425],[198,1927],[748,1014],[1871,-439]],[[40612,86614],[221,1482],[1868,2331],[1914,-775],[503,1583],[-325,2285]],[[56871,66339],[-566,-2755],[-150,-4435],[515,-2187],[81,-2133],[-967,136],[-530,-1036],[-3099,890]],[[52155,54819],[60,-1947],[595,-963],[-100,-2226],[420,-1007]],[[53130,48676],[2217,-2431],[868,-2787]],[[56215,43458],[2109,716],[2173,2406]],[[60497,46580],[366,1072],[1692,259],[206,1313]],[[62761,49224],[-1463,283],[-358,1567],[-1473,2663],[160,2443],[-310,1193],[455,2849]],[[87596,35636],[1149,-953],[1147,492],[-262,1836],[914,1394],[1304,-2598]],[[91848,35807],[1537,4673],[1066,571]],[[94451,41051],[-682,1250],[127,1450],[-1052,2650],[224,1014],[-296,3950],[166,2608],[-710,1207]],[[92228,55180],[-2431,-3259],[456,-2544],[-534,-1162],[-1444,-334],[-209,-997],[-1157,180]],[[86909,47064],[-1615,-470],[-913,1290]],[[84381,47884],[-498,-1817]],[[58084,27094],[-1135,-2522],[116,-1280],[-1241,-1398]],[[54659,20184],[267,-3266],[699,1289],[1455,692],[369,-2088],[1131,-261],[1013,-4279]],[[75631,84437],[-514,1258],[-1349,1324],[-1204,-1171],[-1578,-646],[-1644,-1501],[-1183,-328],[-2161,258]],[[61880,62877],[795,-714],[1412,-3706],[861,-251],[948,-4568]],[[65896,53638],[2394,185],[-181,2198],[1043,762],[1129,-1414],[599,46],[912,-1695]],[[71792,53720],[510,956]],[[72302,54676],[-688,1412],[253,1782],[-474,2757]],[[51879,92638],[-1072,-622],[-1699,1328],[-2372,1301],[-1943,-1125]],[[40612,86614],[235,-2055],[989,-448],[-399,-2075],[-1150,-1434]],[[40287,80602],[2546,-3358],[1030,-384],[-2297,-2841],[-380,-995],[1316,-1751],[22,-1632],[4737,27],[222,-2481],[1052,89]],[[48535,67276],[1099,697]],[[78915,39767],[-559,1423]],[[78356,41190],[-1812,1425],[-1320,3324],[-4,1515],[-1196,1156]],[[74024,48610],[-1448,-8],[22,-2061],[-830,-1892],[-2104,886],[224,-2963],[-571,-1523],[-6,-1569]],[[69311,39480],[883,-1830],[-737,-566]],[[88916,12244],[978,-1797],[1112,-563],[1757,577],[654,1287]],[[93417,11748],[-682,97],[1484,3800],[-154,4128],[1019,-261]],[[95084,19512],[-90,681]],[[94994,20193],[12,2014]],[[95006,22207],[-1811,-178],[-949,-2510],[-1687,978],[-637,-437],[-818,1444]],[[95006,22207],[-109,4550],[-844,790],[730,1540]],[[94783,29087],[-1183,477],[-283,1118],[-1044,405],[-202,1332],[1109,1547],[-1332,1841]],[[80129,14401],[2098,-2811],[953,204]],[[76374,14416],[393,-3665]],[[76767,10751],[1931,-2280]],[[78698,8471],[595,449],[3732,-340]],[[50888,12450],[517,-3648],[887,-1470],[1173,860],[1854,-1165],[100,-1665],[975,-1385]],[[75422,15496],[-1026,-1478],[-731,844],[-724,-1620]],[[72941,13242],[-304,-1680],[369,-5059],[1299,-1682]],[[74305,4821],[258,-64]],[[74563,4757],[612,2746],[823,778],[16,1704],[753,766]],[[73547,20397],[-1201,-4803],[-1314,-1339]],[[71032,14255],[3,-499]],[[71035,13756],[575,-1357],[1331,843]],[[74563,4757],[502,-1429],[1185,-98],[614,1993],[1834,3248]],[[69888,10268],[463,-885],[-810,-2266],[864,-3195],[-57,-3922],[2955,3394],[1002,1427]],[[71035,13756],[-240,-1077],[-1510,-150]],[[71792,53720],[-663,-1202],[231,-2050],[-533,-731],[-2500,-529],[-1296,-3006]],[[67031,46202],[389,-2293],[889,-3047],[1002,-1382]],[[74024,48610],[405,3537]],[[74429,52147],[-625,316]],[[73804,52463],[-1467,1281],[-35,932]],[[73804,52463],[1352,1502]],[[75156,53965],[184,1632],[1157,-116],[2635,-1257],[778,408],[-115,1629],[2054,-1287]],[[81849,54974],[444,595],[-370,2363],[1238,-383]],[[83161,57549],[307,1285]],[[83468,58834],[455,2315],[-983,468],[-462,1390],[754,2606],[1687,587],[581,1238]],[[85500,67438],[-57,948],[-1078,2615],[-889,3590]],[[65896,53638],[831,-2158],[-381,-1938]],[[66346,49542],[63,-2222],[622,-1118]],[[93417,11748],[-48,-3340],[468,-796],[1007,1418],[1233,-1647],[518,435]],[[96595,7818],[-253,1892],[949,1354],[-184,2227],[-1468,979],[-555,5242]],[[70344,24318],[216,-2219],[-2616,-1094],[774,-2731]],[[68718,18274],[1068,-2636],[1246,-1383]],[[96595,7818],[1009,548],[48,-2236],[497,-840],[1393,301],[-443,2610],[254,4358],[-299,951],[172,3745],[515,1701],[258,2651]],[[99999,21607],[-1764,-218],[-392,448],[-2849,-1644]],[[82544,46776],[-415,969],[-949,-963],[-1157,2464],[-974,-305],[-153,3987],[-1412,-29],[-469,-671],[-1859,1737]],[[74429,52147],[1350,-1150],[896,-2269],[1078,-584],[819,-2387],[-216,-4567]],[[63655,39358],[-1463,3646],[-856,957],[-839,2619]],[[56215,43458],[-1750,-954],[-817,-1477]],[[53648,41027],[796,-3117],[-913,-2175],[-351,-1862],[-783,890],[-848,-1348],[301,-1098]],[[51850,32317],[1172,-510],[922,1479]],[[53944,33286],[1665,3195],[1665,1590],[1491,-783],[996,1250]],[[83468,58834],[1150,-2008],[1958,-2145],[1116,2751],[1150,-2243],[1135,315],[67,2214],[716,1016]],[[90760,58734],[-520,1461],[-292,2524],[-1189,-444],[-1600,1267],[-1554,583],[-105,3313]],[[53944,33286],[1186,-79],[1095,-1494]],[[51850,32317],[-1508,-1455],[-103,-1290],[-2629,-1547]],[[99999,21607],[-782,4895],[-2443,7604],[-979,1115]],[[95795,35221],[-1023,-2155],[827,-3044],[-816,-935]],[[65289,16881],[312,1356],[1587,156],[1004,-1271],[526,1152]],[[84381,47884],[-706,1353],[364,1427],[-440,1217],[-1227,489],[-523,2604]],[[53648,41027],[-799,-1240],[-1518,619]],[[51331,40406],[-500,-541],[-439,-2407],[-839,-986],[-2070,1214],[-1207,-3313],[162,-1846]],[[51331,40406],[-1694,3751],[-1100,1138]],[[48537,45295],[-1388,-1206],[-999,290],[-2465,-2269],[-1487,-3443]],[[51293,64204],[885,-1670],[-460,-2842],[907,-889],[-260,-1615],[619,-1043],[-829,-1326]],[[48535,67276],[0,-1473]],[[48535,65803],[220,-3395],[1454,-3456],[-650,-707],[-345,-5101]],[[49214,53144],[1662,-3328],[53,-1122]],[[50929,48694],[1596,-474],[605,456]],[[48535,65803],[-687,-1125],[-765,1066],[-1591,-2874],[-2069,852],[-1479,-95],[-1029,-3586]],[[40915,60041],[2339,-1825],[371,-1116],[-2567,-4518],[-1150,-875],[376,-3586]],[[40284,48121],[1951,-1],[878,911],[491,1556],[2419,2773],[1015,-820],[1467,-8],[709,612]],[[66346,49542],[-1726,1180],[-1859,-1498]],[[50929,48694],[-2192,-2045],[-200,-1354]],[[38970,44875],[-372,-558],[710,-3120]],[[40284,48121],[-1180,-1593]],[[37129,52081],[347,940],[-78,4081],[290,1068],[-303,4546],[-360,1074]],[[37025,63790],[-1030,454]],[[35995,64244],[-2472,-656],[-1418,704],[-617,2173],[73,2295],[-344,1361]],[[29052,70991],[-1003,-1906],[-139,-1663],[-754,-1316],[-2238,-587]],[[35995,64244],[32,4317],[717,3754],[1048,347]],[[37792,72662],[-583,1266],[-1435,769]],[[18459,63740],[-1243,1072],[-1555,-589],[-939,-1233],[-1884,-1351],[-237,-1081],[-1304,-911],[-271,-2058],[-895,-1540],[-320,-1985]],[[40915,60041],[-645,106],[-1375,3066],[-1368,1378],[-502,-801]],[[37792,72662],[1358,-31],[1357,1829],[412,2786],[-632,3356]],[[35714,89092],[-1412,-444],[-738,3179],[-1171,501]],[[32393,92328],[-1246,-4449],[-1550,-3651],[-23,-1886],[-561,-1007],[352,-5381],[-1503,-806],[-27,-3726],[-943,-140],[-1312,1208],[-1151,-1664],[-751,-165],[-619,-1693],[-775,312]],[[38537,99279],[-879,585],[-2698,135],[-1616,-3205],[285,-611],[-1236,-3855]],[[86909,47064],[676,2486],[-1651,2425],[-2073,1807],[-877,2447],[177,1320]],[[92228,55180],[-1468,3554]],[[95795,35221],[-970,2962],[-374,2868]]],"bbox":[138.71191138820006,35.75338410809019,139.89920927398884,36.278535054649126],"transform":{"scale":[0.00001187309758886369,0.000005251561981209191],"translate":[138.71191138820006,35.75338410809019]}}